irapi/__init__.py
irapi/api.py
irapi-0.1.0.dist-info/LICENSE
irapi-0.1.0.dist-info/METADATA
irapi-0.1.0.dist-info/WHEEL
irapi-0.1.0.dist-info/top_level.txt
irapi-0.1.0.dist-info/RECORD
