Metadata-Version: 2.1
Name: irapi
Version: 0.1.0
Summary: InnoRPA common API package
Home-page: https://github.com/kevinblade/rpa-commons
Author: Kevin Cho
Author-email: kevin.innorules@gmail.com
License: UNKNOWN
Platform: UNKNOWN
Classifier: Programming Language :: Python :: 2
Classifier: License :: OSI Approved :: MIT License
Classifier: Operating System :: OS Independent
